LICENSE
MANIFEST.in
README.md
setup.py
version.py
src/transgene/__init__.py
src/transgene/common.py
src/transgene/core.py
src/transgene/fusion.py
src/transgene/indel.py
src/transgene/snv.py
src/transgene/version.py
src/transgene.egg-info/PKG-INFO
src/transgene.egg-info/SOURCES.txt
src/transgene.egg-info/dependency_links.txt
src/transgene.egg-info/entry_points.txt
src/transgene.egg-info/not-zip-safe
src/transgene.egg-info/requires.txt
src/transgene.egg-info/top_level.txt