Metadata-Version: 1.0
Name: transgene
Version: 2.6.2
Summary: Translation of genomic events to proteomic space
Home-page: http://github.com/arkal/transgene
Author: Arjun Arkal Rao
Author-email: aarao@ucsc.edu
License: Apache
Platform: UNKNOWN
